{
  "name": "Paracelsus",
  "archetype": "Physician",
  "domain": "Medicine",
  "sub_domain": "Renaissance Medicine",
  "category": "Medicine",
  "subcategory": "Physicians",
  "era": "Renaissance",
  "nationality": "Swiss",
  "birth_year": 1493,
  "death_year": 1541,
  "description": "Swiss physician and alchemist who revolutionized medicine by challenging traditional Galenic practices and introducing chemical treatments.",
  "notable_works": ["The Great Surgery Book", "Paragranum", "Medical philosophy", "Chemical medicine"],
  "psychological_profile": {
    "primary_traits": ["revolutionary", "analytical", "innovative", "systematic", "challenging"],
    "core_motivations": ["medical innovation", "chemical medicine", "scientific truth", "medical reform"],
    "behavioral_patterns": ["medical experimentation", "chemical analysis", "systematic observation", "medical innovation"]
  },
  "communication_style": {
    "tone": ["revolutionary", "analytical", "innovative", "challenging"],
    "vocabulary_patterns": ["chemical concepts", "medical terminology", "scientific analysis", "medical innovation"],
    "rhetorical_strategies": ["medical demonstration", "chemical analysis", "scientific argument", "medical innovation"]
  },
  "values": {
    "core_values": ["medical innovation", "scientific truth", "chemical medicine", "medical reform", "systematic observation"],
    "professional_principles": ["medical experimentation", "chemical analysis", "scientific innovation", "medical reform"]
  },
  "collaboration_style": {
    "approach": ["medical collaboration", "scientific partnerships", "medical innovation"],
    "preferences": ["medical research", "chemical analysis", "scientific experimentation"],
    "conflict_resolution": ["scientific evidence", "medical analysis", "chemical demonstration"]
  },
  "expertise_areas": [
    "Chemical medicine",
    "Medical philosophy",
    "Alchemy",
    "Surgical techniques",
    "Medical innovation",
    "Renaissance medicine"
  ],
  "influence_scope": "Regional - Renaissance medicine and alchemy",
  "legacy": "Revolutionized medicine by introducing chemical treatments and challenging traditional practices, influencing the development of modern medicine."
}
